leberschuss/__init__.py
leberschuss/main.py
leberschuss-0.2.1.dist-info/LICENSE
leberschuss-0.2.1.dist-info/METADATA
leberschuss-0.2.1.dist-info/WHEEL
leberschuss-0.2.1.dist-info/entry_points.txt
leberschuss-0.2.1.dist-info/top_level.txt
leberschuss-0.2.1.dist-info/RECORD
