Metadata-Version: 2.2
Name: leberschuss
Version: 0.2.1
Summary: OpenAI Query Tool that stores can show the answers of copied text as a notification, gui, or to clipboard.
Author-email: vergelbung <contact.paradize@gmail.com>
License: MIT License
Keywords: openai,exams,hiddenquery
Classifier: Programming Language :: Python :: 3
Classifier: License :: OSI Approved :: MIT License
Classifier: Operating System :: OS Independent
Requires-Python: >=3.7
License-File: LICENSE
Requires-Dist: PyQt5
Requires-Dist: pyperclip
Requires-Dist: openai
